README.rst
setup.py
LightMagic/__init__.py
LightMagic.egg-info/PKG-INFO
LightMagic.egg-info/SOURCES.txt
LightMagic.egg-info/dependency_links.txt
LightMagic.egg-info/requires.txt
LightMagic.egg-info/top_level.txt
LightMagic/db/AioPGModel.py
LightMagic/db/Join.py
LightMagic/db/JoinBase.py
LightMagic/db/JoinSync.py
LightMagic/db/Model.py
LightMagic/db/SynchronousModel.py
LightMagic/db/TornadoModel.py
LightMagic/db/_Model.py
LightMagic/db/_Tools.py
LightMagic/db/__init__.py
LightMagic/db/_sql_generator.py
LightMagic/drivers/SynchronousConnector.py
LightMagic/drivers/__init__.py
LightMagic/services/__init__.py
LightMagic/services/tools.py
LightMagic/types/Bin.py
LightMagic/types/Bool.py
LightMagic/types/Byte.py
LightMagic/types/CardPan.py
LightMagic/types/CryptoAES.py
LightMagic/types/Currency4217.py
LightMagic/types/Date.py
LightMagic/types/DateTime.py
LightMagic/types/Decimal.py
LightMagic/types/Email.py
LightMagic/types/Enum.py
LightMagic/types/Float.py
LightMagic/types/Headers.py
LightMagic/types/IP.py
LightMagic/types/Int.py
LightMagic/types/Json.py
LightMagic/types/Language.py
LightMagic/types/List.py
LightMagic/types/Str.py
LightMagic/types/Time.py
LightMagic/types/TimeDelta.py
LightMagic/types/UUID4.py
LightMagic/types/Url.py
LightMagic/types/_Base.py
LightMagic/types/__init__.py