Metadata-Version: 1.1
Name: LightMagic
Version: 0.3.7
Summary: LightMagic is very simple and quick python3 ORM over momoko/psycopg2.
Home-page: https://github.com/MaxRV/LightMagic
Author: Maxim Radyukov
Author-email: maxim.radyukov@gmail.com
License: MIT
Platform: UNKNOWN
Classifier: Development Status :: 5 - Production/Stable
Classifier: Intended Audience :: Developers
Classifier: License :: OSI Approved :: MIT License
Classifier: Programming Language :: Python
Classifier: Programming Language :: Python :: 3
Classifier: Programming Language :: Python :: Implementation :: CPython
Classifier: Topic :: Database :: Front-Ends
Classifier: Operating System :: OS Independent
